Metadata-Version: 2.1
Name: ezdatabase
Version: 1.5.1
Summary: A simple database wrapper for Python 3
Home-page: UNKNOWN
Author: JJTV
License: MIT
Keywords: database wrapper,ezdatabase,easydatabase,easy database,repl.it database,sql alternative,sqlite
Platform: UNKNOWN
Classifier: Development Status :: 5 - Production/Stable
Classifier: Intended Audience :: Developers
Classifier: License :: OSI Approved :: MIT License
Classifier: Programming Language :: Python :: 3
License-File: LICENSE.txt
